papr_memory_mcp/__init__.py
papr_memory_mcp/core.py
papr_memory_mcp/paprmcp.py
papr_memory_mcp/services/__init__.py
papr_memory_mcp/services/logging_config.py
papr_memory_mcp-0.1.8.dist-info/METADATA
papr_memory_mcp-0.1.8.dist-info/WHEEL
papr_memory_mcp-0.1.8.dist-info/entry_points.txt
papr_memory_mcp-0.1.8.dist-info/top_level.txt
papr_memory_mcp-0.1.8.dist-info/RECORD
