Metadata-Version: 2.4
Name: papr-memory-mcp
Version: 0.1.8
Summary: Papr Memory API integration for MCP (Model Context Protocol) servers
Home-page: https://github.com/Papr-ai/papr_mcpserver
Author: Papr Team
Author-email: Papr Team <support@papr.ai>
Maintainer-email: Papr Team <support@papr.ai>
License-Expression: Apache-2.0
Project-URL: Homepage, https://github.com/Papr-ai/papr_mcpserver
Project-URL: Documentation, https://github.com/Papr-ai/papr_mcpserver/tree/main/python-mcp
Project-URL: Repository, https://github.com/Papr-ai/papr_mcpserver
Project-URL: Issues, https://github.com/Papr-ai/papr_mcpserver/issues
Project-URL: Changelog, https://github.com/Papr-ai/papr_mcpserver/blob/main/python-mcp/CHANGELOG.md
Keywords: mcp,memory,ai,papr,model-context-protocol,fastmcp
Classifier: Development Status :: 4 - Beta
Classifier: Intended Audience :: Developers
Classifier: Programming Language :: Python :: 3
Classifier: Programming Language :: Python :: 3.10
Classifier: Programming Language :: Python :: 3.11
Classifier: Programming Language :: Python :: 3.12
Classifier: Topic :: Software Development :: Libraries :: Python Modules
Classifier: Topic :: Scientific/Engineering :: Artificial Intelligence
Classifier: Topic :: Communications
Classifier: Operating System :: OS Independent
Requires-Python: >=3.10
Requires-Dist: fastmcp>=2.10.5
Requires-Dist: fastapi>=0.110.0
Requires-Dist: httpx>=0.26.0
Requires-Dist: pydantic>=2.0.0
Requires-Dist: python-dotenv>=1.0.0
Requires-Dist: papr-memory>=1.0.0
Requires-Dist: requests>=2.31.0
Requires-Dist: pyyaml>=6.0.0
Requires-Dist: mcp>=1.10.1
Provides-Extra: dev
Requires-Dist: debugpy; extra == "dev"
Requires-Dist: flask>=2.0.0; extra == "dev"
Requires-Dist: flask-cors>=3.0.0; extra == "dev"
Requires-Dist: flask-socketio>=5.0.0; extra == "dev"
Requires-Dist: python-socketio>=5.0.0; extra == "dev"
Requires-Dist: eventlet>=0.30.0; extra == "dev"
Provides-Extra: test
Requires-Dist: pytest>=7.0.0; extra == "test"
Requires-Dist: pytest-asyncio>=0.21.0; extra == "test"
Requires-Dist: pytest-cov>=4.1.0; extra == "test"
Provides-Extra: ml
Requires-Dist: numpy>=1.24.0; extra == "ml"
Requires-Dist: scipy>=1.11.0; extra == "ml"
Requires-Dist: langchain-community>=0.0.10; extra == "ml"
Requires-Dist: ollama>=0.1.6; extra == "ml"
Requires-Dist: sentence-transformers>=2.2.2; extra == "ml"
Requires-Dist: transformers>=4.36.0; extra == "ml"
Requires-Dist: langchain>=0.1.0; extra == "ml"
Provides-Extra: all
Requires-Dist: papr-memory-mcp[dev,ml,test]; extra == "all"
Dynamic: author
Dynamic: home-page
Dynamic: requires-python
